odoo/addons/sm_donation_crm/__init__.py
odoo/addons/sm_donation_crm/__manifest__.py
odoo/addons/sm_donation_crm/data/crm_stage_data.xml
odoo/addons/sm_donation_crm/data/crm_team_data.xml
odoo/addons/sm_donation_crm/data/utm_source_data.xml
odoo/addons/sm_donation_crm/models/__init__.py
odoo/addons/sm_donation_crm/models/crm_team.py
odoo/addons/sm_donation_crm/services/__init__.py
odoo/addons/sm_donation_crm/services/crm_lead_service.py
odoo/addons/sm_donation_crm/services/schemas.py
odoo/addons/sm_donation_crm/views/crm_lead_views.xml
odoo12_addon_sm_donation_crm-12.0.0.0.2.dist-info/METADATA
odoo12_addon_sm_donation_crm-12.0.0.0.2.dist-info/WHEEL
odoo12_addon_sm_donation_crm-12.0.0.0.2.dist-info/top_level.txt
odoo12_addon_sm_donation_crm-12.0.0.0.2.dist-info/RECORD
