Metadata-Version: 2.1
Name: odoo12-addon-sm-donation-crm
Version: 12.0.0.0.2
Summary: Manage donation in crm.lead
Home-page: https://git.coopdevs.org/coopdevs/odoo/odoo-addons/vertical-carsharing
Author: Som Mobilitat
Classifier: Programming Language :: Python
Classifier: Framework :: Odoo
Classifier: Framework :: Odoo :: 12.0
Requires-Python: >=3.5
Requires-Dist: odoo12-addon-crm-metadata
Requires-Dist: odoo12-addon-vertical-carsharing
Requires-Dist: odoo (<12.1dev,>=12.0a)
